fmvmm/__init__.py
fmvmm/distributions/__init__.py
fmvmm/distributions/dirichlet.py
fmvmm/distributions/gig.py
fmvmm/distributions/multivariate_genhyperbolic.py
fmvmm/distributions/multivariate_genskewt.py
fmvmm/distributions/multivariate_hyperbolic.py
fmvmm/distributions/multivariate_norm.py
fmvmm/distributions/multivariate_norminvgauss.py
fmvmm/distributions/multivariate_skew_laplace.py
fmvmm/distributions/multivariate_skew_t_smsn.py
fmvmm/distributions/multivariate_skewnorm.py
fmvmm/distributions/multivariate_skewnorm_cont.py
fmvmm/distributions/multivariate_skewslash.py
fmvmm/distributions/multivariate_slash.py
fmvmm/distributions/multivariate_t.py
fmvmm/distributions/multivariate_vargamma.py
fmvmm/distributions/py_gig.py
fmvmm/mixsmsn/__init__.py
fmvmm/mixsmsn/dens.py
fmvmm/mixsmsn/gen.py
fmvmm/mixsmsn/information_matrix_smsn.py
fmvmm/mixtures/DMM_Hard.py
fmvmm/mixtures/DMM_Soft.py
fmvmm/mixtures/FMVMM.py
fmvmm/mixtures/MixGHD.py
fmvmm/mixtures/__init__.py
fmvmm/mixtures/_base.py
fmvmm/mixtures/mixmgh.py
fmvmm/mixtures/skewcontmix_smsn.py
fmvmm/mixtures/skewlaplacemix.py
fmvmm/mixtures/skewnormmix_smsn.py
fmvmm/mixtures/skewslashmix_smsn.py
fmvmm/mixtures/skewtmix_smsn.py
fmvmm/mixtures/slashmix_smsn.py
fmvmm/mixtures/tmix_smsn.py
fmvmm/utils/__init__.py
fmvmm/utils/dirichlet.py
fmvmm/utils/simplex.py
fmvmm/utils/utils_dmm.py
fmvmm/utils/utils_fmm.py
fmvmm/utils/utils_mixture.py
fmvmm-2.0.9.dist-info/licenses/LICENSE
fmvmm-2.0.9.dist-info/METADATA
fmvmm-2.0.9.dist-info/WHEEL
fmvmm-2.0.9.dist-info/entry_points.txt
fmvmm-2.0.9.dist-info/top_level.txt
fmvmm-2.0.9.dist-info/RECORD
