Metadata-Version: 2.4
Name: fmvmm
Version: 2.0.9
Summary: Flexible Multivariate Mixture Model
Home-page: https://github.com/samyajoypal/fmvmm
Author: Samyajoy Pal
Author-email: palsamyajoy@gmail.com
Project-URL: Github, https://github.com/samyajoypal/fmvmm
Classifier: Programming Language :: Python :: 3
Classifier: License :: OSI Approved :: MIT License
Classifier: Operating System :: OS Independent
Requires-Python: >=3.8
License-File: LICENSE
Requires-Dist: conorm~=1.2.0
Requires-Dist: matplotlib~=3.7
Requires-Dist: numpy<1.26,>=1.24
Requires-Dist: pandas<2.2,>=2.0
Requires-Dist: scikit-learn<1.8,>=1.6
Requires-Dist: scipy<1.11,>=1.9
Requires-Dist: setuptools
Dynamic: author
Dynamic: author-email
Dynamic: classifier
Dynamic: description
Dynamic: description-content-type
Dynamic: home-page
Dynamic: license-file
Dynamic: project-url
Dynamic: requires-dist
Dynamic: requires-python
Dynamic: summary
